[
  {
    "home_team": "Orlando Magic",
    "away_team": "Boston Celtics",
    "commence_time": "2023-11-24T19:30:00Z",
    "num_bookmakers": 14,
    "moneyline": {
      "home": 171,
      "away": -205
    },
    "spread": {
      "line": 5.0,
      "home_odds": -110,
      "away_odds": -109
    },
    "total": {
      "line": 223.4,
      "over_odds": -109,
      "under_odds": -110
    }
  },
  {
    "home_team": "Memphis Grizzlies",
    "away_team": "Phoenix Suns",
    "commence_time": "2023-11-24T22:00:00Z",
    "num_bookmakers": 12,
    "moneyline": {
      "home": 239,
      "away": -297
    },
    "spread": {
      "line": 7.5,
      "home_odds": -110,
      "away_odds": -109
    },
    "total": {
      "line": 223.5,
      "over_odds": -90,
      "under_odds": -111
    }
  },
  {
    "home_team": "Toronto Raptors",
    "away_team": "Chicago Bulls",
    "commence_time": "2023-11-25T00:30:00Z",
    "num_bookmakers": 14,
    "moneyline": {
      "home": -212,
      "away": 175
    },
    "spread": {
      "line": -5.1,
      "home_odds": -110,
      "away_odds": -109
    },
    "total": {
      "line": 216.8,
      "over_odds": -109,
      "under_odds": -110
    }
  },
  {
    "home_team": "New York Knicks",
    "away_team": "Miami Heat",
    "commence_time": "2023-11-25T00:30:00Z",
    "num_bookmakers": 14,
    "moneyline": {
      "home": -226,
      "away": 184
    },
    "spread": {
      "line": -5.8,
      "home_odds": -109,
      "away_odds": -110
    },
    "total": {
      "line": 211.7,
      "over_odds": -109,
      "under_odds": -109
    }
  },
  {
    "home_team": "Houston Rockets",
    "away_team": "Denver Nuggets",
    "commence_time": "2023-11-25T01:00:00Z",
    "num_bookmakers": 14,
    "moneyline": {
      "home": 127,
      "away": -150
    },
    "spread": {
      "line": 3.1,
      "home_odds": -109,
      "away_odds": -109
    },
    "total": {
      "line": 216.5,
      "over_odds": -109,
      "under_odds": -109
    }
  },
  {
    "home_team": "Indiana Pacers",
    "away_team": "Detroit Pistons",
    "commence_time": "2023-11-25T01:00:00Z",
    "num_bookmakers": 14,
    "moneyline": {
      "home": -361,
      "away": 283
    },
    "spread": {
      "line": -8.6,
      "home_odds": -111,
      "away_odds": -108
    },
    "total": {
      "line": 247.4,
      "over_odds": -109,
      "under_odds": -109
    }
  },
  {
    "home_team": "Milwaukee Bucks",
    "away_team": "Washington Wizards",
    "commence_time": "2023-11-25T01:00:00Z",
    "num_bookmakers": 14,
    "moneyline": {
      "home": -944,
      "away": 611
    },
    "spread": {
      "line": -13.4,
      "home_odds": -110,
      "away_odds": -109
    },
    "total": {
      "line": 247.0,
      "over_odds": -110,
      "under_odds": -109
    }
  },
  {
    "home_team": "Minnesota Timberwolves",
    "away_team": "Sacramento Kings",
    "commence_time": "2023-11-25T01:00:00Z",
    "num_bookmakers": 14,
    "moneyline": {
      "home": -176,
      "away": 149
    },
    "spread": {
      "line": -4.1,
      "home_odds": -110,
      "away_odds": -109
    },
    "total": {
      "line": 229.6,
      "over_odds": -109,
      "under_odds": -109
    }
  },
  {
    "home_team": "Golden State Warriors",
    "away_team": "San Antonio Spurs",
    "commence_time": "2023-11-25T03:00:00Z",
    "num_bookmakers": 14,
    "moneyline": {
      "home": -485,
      "away": 367
    },
    "spread": {
      "line": -10.0,
      "home_odds": -110,
      "away_odds": -109
    },
    "total": {
      "line": 228.6,
      "over_odds": -109,
      "under_odds": -109
    }
  },
  {
    "home_team": "Los Angeles Clippers",
    "away_team": "New Orleans Pelicans",
    "commence_time": "2023-11-25T03:30:00Z",
    "num_bookmakers": 14,
    "moneyline": {
      "home": -223,
      "away": 184
    },
    "spread": {
      "line": -5.6,
      "home_odds": -108,
      "away_odds": -110
    },
    "total": {
      "line": 224.0,
      "over_odds": -110,
      "under_odds": -109
    }
  },
  {
    "home_team": "New York Knicks",
    "away_team": "Milwaukee Bucks",
    "commence_time": "2023-12-25T17:00:00Z",
    "num_bookmakers": 3,
    "moneyline": {
      "home": 140,
      "away": -172
    },
    "spread": {
      "line": 3.8,
      "home_odds": -110,
      "away_odds": -110
    },
    "total": {
      "line": null,
      "over_odds": null,
      "under_odds": null
    }
  },
  {
    "home_team": "Denver Nuggets",
    "away_team": "Golden State Warriors",
    "commence_time": "2023-12-25T19:30:00Z",
    "num_bookmakers": 3,
    "moneyline": {
      "home": -205,
      "away": 166
    },
    "spread": {
      "line": -5.0,
      "home_odds": -111,
      "away_odds": -109
    },
    "total": {
      "line": null,
      "over_odds": null,
      "under_odds": null
    }
  },
  {
    "home_team": "Los Angeles Lakers",
    "away_team": "Boston Celtics",
    "commence_time": "2023-12-25T22:00:00Z",
    "num_bookmakers": 3,
    "moneyline": {
      "home": 103,
      "away": -124
    },
    "spread": {
      "line": 1.5,
      "home_odds": -108,
      "away_odds": -112
    },
    "total": {
      "line": null,
      "over_odds": null,
      "under_odds": null
    }
  },
  {
    "home_team": "Miami Heat",
    "away_team": "Philadelphia 76ers",
    "commence_time": "2023-12-26T01:00:00Z",
    "num_bookmakers": 3,
    "moneyline": {
      "home": -127,
      "away": 106
    },
    "spread": {
      "line": -1.8,
      "home_odds": -110,
      "away_odds": -110
    },
    "total": {
      "line": null,
      "over_odds": null,
      "under_odds": null
    }
  },
  {
    "home_team": "Phoenix Suns",
    "away_team": "Dallas Mavericks",
    "commence_time": "2023-12-26T03:30:00Z",
    "num_bookmakers": 3,
    "moneyline": {
      "home": -201,
      "away": 163
    },
    "spread": {
      "line": -5.0,
      "home_odds": -110,
      "away_odds": -110
    },
    "total": {
      "line": null,
      "over_odds": null,
      "under_odds": null
    }
  }
]